<annotation>
	<folder>VOC2007</folder>
	<filename>006471.jpg</filename>
	<source>
		<database>My Database</database>
		<annotation>VOC2007</annotation>
		<image>flickr</image>
		<flickrid>NULL</flickrid>
	</source>
	<owner>
		<flickrid>NULL</flickrid>
		<name>zyk</name>
	</owner>
	<size>
		<width>500</width>
		<height>335</height>
		<depth>3</depth>
	</size>
	<segmented>0</segmented>
	<object>
		<name>111.Loggerhead_Shrike</name>
		<pose>Unspecified</pose>
		<truncated>0</truncated>
		<difficult>0</difficult>
		<bndbox>
			<xmin>205.0</xmin>
			<ymin>134.0</ymin>
			<xmax>419.0</xmax>
			<ymax>277.0</ymax>
		</bndbox>
	</object>
</annotation>
